README.rst
setup.py
Bee/__init__.py
Bee/locator2.py
pppTest.egg-info/PKG-INFO
pppTest.egg-info/SOURCES.txt
pppTest.egg-info/dependency_links.txt
pppTest.egg-info/top_level.txt